glom_dict/__init__.py
glom_dict/__main__.py
glom_dict-0.0.2a0.dist-info/LICENSE
glom_dict-0.0.2a0.dist-info/WHEEL
glom_dict-0.0.2a0.dist-info/METADATA
glom_dict-0.0.2a0.dist-info/RECORD
