Metadata-Version: 2.1
Name: glom-dict
Version: 0.0.2a0
Summary: Custom Dictionary with glom get, set and del methods
Home-page: https://github.com/kilo59/glom-dict
License: MIT
Keywords: glom,dict,nested
Author: Gabriel
Author-email: gabriel59kg@gmail.com
Requires-Python: >=3.6.2,<4.0.0
Classifier: License :: OSI Approved :: MIT License
Classifier: Programming Language :: Python :: 3
Classifier: Programming Language :: Python :: 3.10
Classifier: Programming Language :: Python :: 3.7
Classifier: Programming Language :: Python :: 3.8
Classifier: Programming Language :: Python :: 3.9
Requires-Dist: glom (>=20.11.0,<21.0.0)
Project-URL: Repository, https://github.com/kilo59/glom-dict
